kiwi_release_cli/cli.py
kiwi_release_cli-0.0.2.dist-info/METADATA
kiwi_release_cli-0.0.2.dist-info/WHEEL
kiwi_release_cli-0.0.2.dist-info/entry_points.txt
kiwi_release_cli-0.0.2.dist-info/RECORD
